Metadata-Version: 2.1
Name: sort-methods
Version: 1.0.0
Summary: 5 methods of sort in python
Home-page: https://github.com/rborkv/sort_methods/
Author: Borenkov Roman
Author-email: 
License: UNKNOWN
Platform: any
Requires-Python: >=3.7
